{"Metascore":"88","BoxOffice":"N\/A","Website":"N\/A","imdbRating":"8.0","imdbVotes":"632,629","Ratings":[{"Value":"8.0\/10","Source":"Internet Movie Database"},{"Value":"94%","Source":"Rotten Tomatoes"},{"Value":"88\/100","Source":"Metacritic"}],"Runtime":"118 min","Language":"English","Rated":"R","Production":"See-Saw Films, Bedlam Pictures","Released":"25 Dec 2010","imdbID":"tt1504320","Plot":"England's Prince Albert must ascend the throne as King George VI, but he has a speech impediment. Knowing that the country needs her husband to be able to communicate effectively, Elizabeth hires Lionel Logue, an Australian actor and speech therapist, to help him overcome his stammer. An extraordinary friendship develops between the two men, as Logue uses unconventional means to teach the monarch how to speak with confidence.","Director":"Tom Hooper","Title":"The King's Speech","Actors":"Colin Firth, Helena Bonham Carter, Derek Jacobi, Robert Portal","Response":"True","Type":"movie","Awards":"Won 4 Oscars. Another 105 wins & 205 nominations.","DVD":"N\/A","Year":"2010","Poster":"https:\/\/m.media-amazon.com\/images\/M\/MV5BMzU5MjEwMTg2Nl5BMl5BanBnXkFtZTcwNzM3MTYxNA@@._V1_SX300.jpg","Country":"UK, USA, Australia","Genre":"Biography, Drama, History","Writer":"David Seidler (screenplay)"}
